gql_appsync_cognito_authentication/__init__.py
gql_appsync_cognito_authentication-0.0.1.dist-info/LICENSE
gql_appsync_cognito_authentication-0.0.1.dist-info/METADATA
gql_appsync_cognito_authentication-0.0.1.dist-info/WHEEL
gql_appsync_cognito_authentication-0.0.1.dist-info/top_level.txt
gql_appsync_cognito_authentication-0.0.1.dist-info/RECORD
