Metadata-Version: 2.1
Name: gql-appsync-cognito-authentication
Version: 0.0.1
Summary: An AppSyncAuthentication implementation for gql.transport.aiohttp.AIOHTTPTransport using pycognito
Author: QuiNovas
Author-email: pypi@quinovas.com
Requires-Python: >=3.9
License-File: LICENSE
Requires-Dist: gql[aiohttp] (>=3.0.0)
Requires-Dist: pycognito
